geodb_finder/__init__.py
geodb_finder/data/geolocations.db
geodb_finder-0.2.1.dist-info/METADATA
geodb_finder-0.2.1.dist-info/WHEEL
geodb_finder-0.2.1.dist-info/top_level.txt
geodb_finder-0.2.1.dist-info/RECORD
