Metadata-Version: 2.2
Name: geodb-finder
Version: 0.2.1
Summary: A timezone and geolocation database finder.
Home-page: https://www.esocoding.dev
Author: Gert-jan Poortman
Author-email: info@esocoding.dev
Classifier: Programming Language :: Python :: 3
Classifier: License :: OSI Approved :: MIT License
Classifier: Operating System :: OS Independent
Requires-Python: >=3.7
Requires-Dist: aiosqlite>=0.21.0
Provides-Extra: dev
Requires-Dist: pytest>=8.3.4; extra == "dev"
Requires-Dist: wheel>=0.45.1; extra == "dev"
Dynamic: author
Dynamic: author-email
Dynamic: classifier
Dynamic: description
Dynamic: description-content-type
Dynamic: home-page
Dynamic: provides-extra
Dynamic: requires-dist
Dynamic: requires-python
Dynamic: summary
